js_mw_api/__init__.py
js_mw_api/mwapi.py
js_mw_api-3.4.2.1.dist-info/METADATA
js_mw_api-3.4.2.1.dist-info/WHEEL
js_mw_api-3.4.2.1.dist-info/RECORD
