Metadata-Version: 2.4
Name: js_mw_api
Version: 3.4.2.1
Summary: Moraware API Wrapper for Python
Project-URL: Homepage, https://github.com/JensenSystems/JS_Moraware
Project-URL: Issues, https://github.com/JensenSystems/JS_Moraware/issues
Author-email: Tyler Jensen <Tyler@JensenSystems.co.nz>
Classifier: Operating System :: OS Independent
Classifier: Programming Language :: Python :: 3
Requires-Python: >=3.11
